[
  {
    "行政區別": "鳳林鎮",
    "村里別": "總計",
    "候選人票數": {
      "金色曠野同盟": 1728,
      "蔚藍海岸陣線": 4319,
      "鬱蔥雨林聯盟": 228
    },
    "有效票數": 6275,
    "無效票數": 59,
    "投票數": 6334,
    "已領未投票數": 0,
    "發出票數": 6334,
    "用餘票數": 3416,
    "選舉人數": 9750,
    "投票率": 64.95999908447266
  },
  {
    "行政區別": "鳳林鎮",
    "村里別": "鳳仁里",
    "候選人票數": {
      "金色曠野同盟": 216,
      "蔚藍海岸陣線": 527,
      "鬱蔥雨林聯盟": 23
    },
    "有效票數": 766,
    "無效票數": 9,
    "投票數": 775,
    "已領未投票數": 0,
    "發出票數": 775,
    "用餘票數": 420,
    "選舉人數": 1195,
    "投票率": 64.8499984741211
  },
  {
    "行政區別": "鳳林鎮",
    "村里別": "鳳義里",
    "候選人票數": {
      "金色曠野同盟": 103,
      "蔚藍海岸陣線": 302,
      "鬱蔥雨林聯盟": 14
    },
    "有效票數": 419,
    "無效票數": 9,
    "投票數": 428,
    "已領未投票數": 0,
    "發出票數": 428,
    "用餘票數": 213,
    "選舉人數": 641,
    "投票率": 66.7699966430664
  },
  {
    "行政區別": "鳳林鎮",
    "村里別": "鳳禮里",
    "候選人票數": {
      "金色曠野同盟": 107,
      "蔚藍海岸陣線": 287,
      "鬱蔥雨林聯盟": 21
    },
    "有效票數": 415,
    "無效票數": 3,
    "投票數": 418,
    "已領未投票數": 0,
    "發出票數": 418,
    "用餘票數": 179,
    "選舉人數": 597,
    "投票率": 70.0199966430664
  },
  {
    "行政區別": "鳳林鎮",
    "村里別": "鳳智里",
    "候選人票數": {
      "金色曠野同盟": 170,
      "蔚藍海岸陣線": 595,
      "鬱蔥雨林聯盟": 24
    },
    "有效票數": 789,
    "無效票數": 1,
    "投票數": 790,
    "已領未投票數": 0,
    "發出票數": 790,
    "用餘票數": 351,
    "選舉人數": 1141,
    "投票率": 69.23999786376953
  },
  {
    "行政區別": "鳳林鎮",
    "村里別": "鳳信里",
    "候選人票數": {
      "金色曠野同盟": 146,
      "蔚藍海岸陣線": 615,
      "鬱蔥雨林聯盟": 38
    },
    "有效票數": 799,
    "無效票數": 11,
    "投票數": 810,
    "已領未投票數": 0,
    "發出票數": 810,
    "用餘票數": 490,
    "選舉人數": 1300,
    "投票率": 62.310001373291016
  },
  {
    "行政區別": "鳳林鎮",
    "村里別": "山興里",
    "候選人票數": {
      "金色曠野同盟": 65,
      "蔚藍海岸陣線": 228,
      "鬱蔥雨林聯盟": 11
    },
    "有效票數": 304,
    "無效票數": 2,
    "投票數": 306,
    "已領未投票數": 0,
    "發出票數": 306,
    "用餘票數": 211,
    "選舉人數": 517,
    "投票率": 59.189998626708984
  },
  {
    "行政區別": "鳳林鎮",
    "村里別": "大榮里",
    "候選人票數": {
      "金色曠野同盟": 267,
      "蔚藍海岸陣線": 473,
      "鬱蔥雨林聯盟": 27
    },
    "有效票數": 767,
    "無效票數": 10,
    "投票數": 777,
    "已領未投票數": 0,
    "發出票數": 777,
    "用餘票數": 459,
    "選舉人數": 1236,
    "投票率": 62.86000061035156
  },
  {
    "行政區別": "鳳林鎮",
    "村里別": "北林里",
    "候選人票數": {
      "金色曠野同盟": 170,
      "蔚藍海岸陣線": 193,
      "鬱蔥雨林聯盟": 13
    },
    "有效票數": 376,
    "無效票數": 2,
    "投票數": 378,
    "已領未投票數": 0,
    "發出票數": 378,
    "用餘票數": 224,
    "選舉人數": 602,
    "投票率": 62.790000915527344
  },
  {
    "行政區別": "鳳林鎮",
    "村里別": "南平里",
    "候選人票數": {
      "金色曠野同盟": 137,
      "蔚藍海岸陣線": 229,
      "鬱蔥雨林聯盟": 12
    },
    "有效票數": 378,
    "無效票數": 2,
    "投票數": 380,
    "已領未投票數": 0,
    "發出票數": 380,
    "用餘票數": 200,
    "選舉人數": 580,
    "投票率": 65.5199966430664
  },
  {
    "行政區別": "鳳林鎮",
    "村里別": "林榮里",
    "候選人票數": {
      "金色曠野同盟": 129,
      "蔚藍海岸陣線": 406,
      "鬱蔥雨林聯盟": 20
    },
    "有效票數": 555,
    "無效票數": 6,
    "投票數": 561,
    "已領未投票數": 0,
    "發出票數": 561,
    "用餘票數": 266,
    "選舉人數": 827,
    "投票率": 67.83999633789062
  },
  {
    "行政區別": "鳳林鎮",
    "村里別": "長橋里",
    "候選人票數": {
      "金色曠野同盟": 204,
      "蔚藍海岸陣線": 397,
      "鬱蔥雨林聯盟": 23
    },
    "有效票數": 624,
    "無效票數": 3,
    "投票數": 627,
    "已領未投票數": 0,
    "發出票數": 627,
    "用餘票數": 365,
    "選舉人數": 992,
    "投票率": 63.209999084472656
  },
  {
    "行政區別": "鳳林鎮",
    "村里別": "森榮里",
    "候選人票數": {
      "金色曠野同盟": 14,
      "蔚藍海岸陣線": 67,
      "鬱蔥雨林聯盟": 2
    },
    "有效票數": 83,
    "無效票數": 1,
    "投票數": 84,
    "已領未投票數": 0,
    "發出票數": 84,
    "用餘票數": 38,
    "選舉人數": 122,
    "投票率": 68.8499984741211
  }
]