[
  {
    "行政區別": "烈嶼鄉",
    "村里別": "總計",
    "候選人票數": {
      "金色曠野同盟": 175,
      "蔚藍海岸陣線": 3023,
      "鬱蔥雨林聯盟": 69
    },
    "有效票數": 3267,
    "無效票數": 35,
    "投票數": 3302,
    "已領未投票數": 0,
    "發出票數": 3302,
    "用餘票數": 4650,
    "選舉人數": 7952,
    "投票率": 41.52000045776367
  },
  {
    "行政區別": "烈嶼鄉",
    "村里別": "林湖村",
    "候選人票數": {
      "金色曠野同盟": 61,
      "蔚藍海岸陣線": 980,
      "鬱蔥雨林聯盟": 27
    },
    "有效票數": 1068,
    "無效票數": 6,
    "投票數": 1074,
    "已領未投票數": 0,
    "發出票數": 1074,
    "用餘票數": 1300,
    "選舉人數": 2374,
    "投票率": 45.2400016784668
  },
  {
    "行政區別": "烈嶼鄉",
    "村里別": "黃埔村",
    "候選人票數": {
      "金色曠野同盟": 28,
      "蔚藍海岸陣線": 376,
      "鬱蔥雨林聯盟": 2
    },
    "有效票數": 406,
    "無效票數": 11,
    "投票數": 417,
    "已領未投票數": 0,
    "發出票數": 417,
    "用餘票數": 608,
    "選舉人數": 1025,
    "投票率": 40.68000030517578
  },
  {
    "行政區別": "烈嶼鄉",
    "村里別": "西口村",
    "候選人票數": {
      "金色曠野同盟": 30,
      "蔚藍海岸陣線": 540,
      "鬱蔥雨林聯盟": 8
    },
    "有效票數": 578,
    "無效票數": 8,
    "投票數": 586,
    "已領未投票數": 0,
    "發出票數": 586,
    "用餘票數": 1029,
    "選舉人數": 1615,
    "投票率": 36.279998779296875
  },
  {
    "行政區別": "烈嶼鄉",
    "村里別": "上林村",
    "候選人票數": {
      "金色曠野同盟": 25,
      "蔚藍海岸陣線": 385,
      "鬱蔥雨林聯盟": 11
    },
    "有效票數": 421,
    "無效票數": 2,
    "投票數": 423,
    "已領未投票數": 0,
    "發出票數": 423,
    "用餘票數": 612,
    "選舉人數": 1035,
    "投票率": 40.869998931884766
  },
  {
    "行政區別": "烈嶼鄉",
    "村里別": "上岐村",
    "候選人票數": {
      "金色曠野同盟": 31,
      "蔚藍海岸陣線": 742,
      "鬱蔥雨林聯盟": 21
    },
    "有效票數": 794,
    "無效票數": 8,
    "投票數": 802,
    "已領未投票數": 0,
    "發出票數": 802,
    "用餘票數": 1101,
    "選舉人數": 1903,
    "投票率": 42.13999938964844
  }
]