[
  {
    "行政區別": "岡山區",
    "村里別": "總計",
    "候選人票數": {
      "金色曠野同盟": 29593,
      "蔚藍海岸陣線": 26952,
      "鬱蔥雨林聯盟": 1711
    },
    "有效票數": 58256,
    "無效票數": 407,
    "投票數": 58663,
    "已領未投票數": 1,
    "發出票數": 58664,
    "用餘票數": 16366,
    "選舉人數": 75030,
    "投票率": 78.19000244140625
  },
  {
    "行政區別": "岡山區",
    "村里別": "平安里",
    "候選人票數": {
      "金色曠野同盟": 496,
      "蔚藍海岸陣線": 430,
      "鬱蔥雨林聯盟": 23
    },
    "有效票數": 949,
    "無效票數": 3,
    "投票數": 952,
    "已領未投票數": 0,
    "發出票數": 952,
    "用餘票數": 273,
    "選舉人數": 1225,
    "投票率": 77.70999908447266
  },
  {
    "行政區別": "岡山區",
    "村里別": "岡山里",
    "候選人票數": {
      "金色曠野同盟": 1541,
      "蔚藍海岸陣線": 1279,
      "鬱蔥雨林聯盟": 82
    },
    "有效票數": 2902,
    "無效票數": 22,
    "投票數": 2924,
    "已領未投票數": 0,
    "發出票數": 2924,
    "用餘票數": 1071,
    "選舉人數": 3995,
    "投票率": 73.19000244140625
  },
  {
    "行政區別": "岡山區",
    "村里別": "壽天里",
    "候選人票數": {
      "金色曠野同盟": 1218,
      "蔚藍海岸陣線": 1231,
      "鬱蔥雨林聯盟": 69
    },
    "有效票數": 2518,
    "無效票數": 14,
    "投票數": 2532,
    "已領未投票數": 0,
    "發出票數": 2532,
    "用餘票數": 686,
    "選舉人數": 3218,
    "投票率": 78.68000030517578
  },
  {
    "行政區別": "岡山區",
    "村里別": "維仁里",
    "候選人票數": {
      "金色曠野同盟": 441,
      "蔚藍海岸陣線": 333,
      "鬱蔥雨林聯盟": 22
    },
    "有效票數": 796,
    "無效票數": 4,
    "投票數": 800,
    "已領未投票數": 0,
    "發出票數": 800,
    "用餘票數": 257,
    "選舉人數": 1057,
    "投票率": 75.69000244140625
  },
  {
    "行政區別": "岡山區",
    "村里別": "後紅里",
    "候選人票數": {
      "金色曠野同盟": 1208,
      "蔚藍海岸陣線": 1330,
      "鬱蔥雨林聯盟": 78
    },
    "有效票數": 2616,
    "無效票數": 14,
    "投票數": 2630,
    "已領未投票數": 0,
    "發出票數": 2630,
    "用餘票數": 840,
    "選舉人數": 3470,
    "投票率": 75.79000091552734
  },
  {
    "行政區別": "岡山區",
    "村里別": "大遼里",
    "候選人票數": {
      "金色曠野同盟": 748,
      "蔚藍海岸陣線": 209,
      "鬱蔥雨林聯盟": 16
    },
    "有效票數": 973,
    "無效票數": 6,
    "投票數": 979,
    "已領未投票數": 0,
    "發出票數": 979,
    "用餘票數": 250,
    "選舉人數": 1229,
    "投票率": 79.66000366210938
  },
  {
    "行政區別": "岡山區",
    "村里別": "忠孝里",
    "候選人票數": {
      "金色曠野同盟": 254,
      "蔚藍海岸陣線": 1899,
      "鬱蔥雨林聯盟": 79
    },
    "有效票數": 2232,
    "無效票數": 6,
    "投票數": 2238,
    "已領未投票數": 0,
    "發出票數": 2238,
    "用餘票數": 603,
    "選舉人數": 2841,
    "投票率": 78.77999877929688
  },
  {
    "行政區別": "岡山區",
    "村里別": "和平里",
    "候選人票數": {
      "金色曠野同盟": 134,
      "蔚藍海岸陣線": 101,
      "鬱蔥雨林聯盟": 7
    },
    "有效票數": 242,
    "無效票數": 2,
    "投票數": 244,
    "已領未投票數": 0,
    "發出票數": 244,
    "用餘票數": 46,
    "選舉人數": 290,
    "投票率": 84.13999938964844
  },
  {
    "行政區別": "岡山區",
    "村里別": "前峰里",
    "候選人票數": {
      "金色曠野同盟": 1111,
      "蔚藍海岸陣線": 918,
      "鬱蔥雨林聯盟": 48
    },
    "有效票數": 2077,
    "無效票數": 22,
    "投票數": 2099,
    "已領未投票數": 1,
    "發出票數": 2100,
    "用餘票數": 590,
    "選舉人數": 2690,
    "投票率": 78.02999877929688
  },
  {
    "行政區別": "岡山區",
    "村里別": "劉厝里",
    "候選人票數": {
      "金色曠野同盟": 753,
      "蔚藍海岸陣線": 343,
      "鬱蔥雨林聯盟": 24
    },
    "有效票數": 1120,
    "無效票數": 8,
    "投票數": 1128,
    "已領未投票數": 0,
    "發出票數": 1128,
    "用餘票數": 253,
    "選舉人數": 1381,
    "投票率": 81.68000030517578
  },
  {
    "行政區別": "岡山區",
    "村里別": "協和里",
    "候選人票數": {
      "金色曠野同盟": 1261,
      "蔚藍海岸陣線": 1160,
      "鬱蔥雨林聯盟": 71
    },
    "有效票數": 2492,
    "無效票數": 14,
    "投票數": 2506,
    "已領未投票數": 0,
    "發出票數": 2506,
    "用餘票數": 685,
    "選舉人數": 3191,
    "投票率": 78.52999877929688
  },
  {
    "行政區別": "岡山區",
    "村里別": "後協里",
    "候選人票數": {
      "金色曠野同盟": 1612,
      "蔚藍海岸陣線": 2042,
      "鬱蔥雨林聯盟": 113
    },
    "有效票數": 3767,
    "無效票數": 28,
    "投票數": 3795,
    "已領未投票數": 0,
    "發出票數": 3795,
    "用餘票數": 1128,
    "選舉人數": 4923,
    "投票率": 77.08999633789062
  },
  {
    "行政區別": "岡山區",
    "村里別": "信義里",
    "候選人票數": {
      "金色曠野同盟": 462,
      "蔚藍海岸陣線": 814,
      "鬱蔥雨林聯盟": 34
    },
    "有效票數": 1310,
    "無效票數": 12,
    "投票數": 1322,
    "已領未投票數": 0,
    "發出票數": 1322,
    "用餘票數": 389,
    "選舉人數": 1711,
    "投票率": 77.26000213623047
  },
  {
    "行政區別": "岡山區",
    "村里別": "潭底里",
    "候選人票數": {
      "金色曠野同盟": 445,
      "蔚藍海岸陣線": 194,
      "鬱蔥雨林聯盟": 12
    },
    "有效票數": 651,
    "無效票數": 6,
    "投票數": 657,
    "已領未投票數": 0,
    "發出票數": 657,
    "用餘票數": 108,
    "選舉人數": 765,
    "投票率": 85.87999725341797
  },
  {
    "行政區別": "岡山區",
    "村里別": "三和里",
    "候選人票數": {
      "金色曠野同盟": 477,
      "蔚藍海岸陣線": 158,
      "鬱蔥雨林聯盟": 29
    },
    "有效票數": 664,
    "無效票數": 7,
    "投票數": 671,
    "已領未投票數": 0,
    "發出票數": 671,
    "用餘票數": 182,
    "選舉人數": 853,
    "投票率": 78.66000366210938
  },
  {
    "行政區別": "岡山區",
    "村里別": "仁壽里",
    "候選人票數": {
      "金色曠野同盟": 1279,
      "蔚藍海岸陣線": 1218,
      "鬱蔥雨林聯盟": 78
    },
    "有效票數": 2575,
    "無效票數": 14,
    "投票數": 2589,
    "已領未投票數": 0,
    "發出票數": 2589,
    "用餘票數": 734,
    "選舉人數": 3323,
    "投票率": 77.91000366210938
  },
  {
    "行政區別": "岡山區",
    "村里別": "碧紅里",
    "候選人票數": {
      "金色曠野同盟": 1365,
      "蔚藍海岸陣線": 1154,
      "鬱蔥雨林聯盟": 79
    },
    "有效票數": 2598,
    "無效票數": 19,
    "投票數": 2617,
    "已領未投票數": 0,
    "發出票數": 2617,
    "用餘票數": 791,
    "選舉人數": 3408,
    "投票率": 76.79000091552734
  },
  {
    "行政區別": "岡山區",
    "村里別": "程香里",
    "候選人票數": {
      "金色曠野同盟": 1279,
      "蔚藍海岸陣線": 1385,
      "鬱蔥雨林聯盟": 87
    },
    "有效票數": 2751,
    "無效票數": 19,
    "投票數": 2770,
    "已領未投票數": 0,
    "發出票數": 2770,
    "用餘票數": 790,
    "選舉人數": 3560,
    "投票率": 77.80999755859375
  },
  {
    "行政區別": "岡山區",
    "村里別": "竹圍里",
    "候選人票數": {
      "金色曠野同盟": 2241,
      "蔚藍海岸陣線": 1952,
      "鬱蔥雨林聯盟": 134
    },
    "有效票數": 4327,
    "無效票數": 23,
    "投票數": 4350,
    "已領未投票數": 0,
    "發出票數": 4350,
    "用餘票數": 1228,
    "選舉人數": 5578,
    "投票率": 77.9800033569336
  },
  {
    "行政區別": "岡山區",
    "村里別": "台上里",
    "候選人票數": {
      "金色曠野同盟": 2046,
      "蔚藍海岸陣線": 1451,
      "鬱蔥雨林聯盟": 111
    },
    "有效票數": 3608,
    "無效票數": 25,
    "投票數": 3633,
    "已領未投票數": 0,
    "發出票數": 3633,
    "用餘票數": 1071,
    "選舉人數": 4704,
    "投票率": 77.2300033569336
  },
  {
    "行政區別": "岡山區",
    "村里別": "灣裡里",
    "候選人票數": {
      "金色曠野同盟": 732,
      "蔚藍海岸陣線": 520,
      "鬱蔥雨林聯盟": 34
    },
    "有效票數": 1286,
    "無效票數": 14,
    "投票數": 1300,
    "已領未投票數": 0,
    "發出票數": 1300,
    "用餘票數": 335,
    "選舉人數": 1635,
    "投票率": 79.51000213623047
  },
  {
    "行政區別": "岡山區",
    "村里別": "白米里",
    "候選人票數": {
      "金色曠野同盟": 685,
      "蔚藍海岸陣線": 553,
      "鬱蔥雨林聯盟": 62
    },
    "有效票數": 1300,
    "無效票數": 9,
    "投票數": 1309,
    "已領未投票數": 0,
    "發出票數": 1309,
    "用餘票數": 331,
    "選舉人數": 1640,
    "投票率": 79.81999969482422
  },
  {
    "行政區別": "岡山區",
    "村里別": "石潭里",
    "候選人票數": {
      "金色曠野同盟": 845,
      "蔚藍海岸陣線": 516,
      "鬱蔥雨林聯盟": 31
    },
    "有效票數": 1392,
    "無效票數": 5,
    "投票數": 1397,
    "已領未投票數": 0,
    "發出票數": 1397,
    "用餘票數": 341,
    "選舉人數": 1738,
    "投票率": 80.37999725341797
  },
  {
    "行政區別": "岡山區",
    "村里別": "福興里",
    "候選人票數": {
      "金色曠野同盟": 436,
      "蔚藍海岸陣線": 335,
      "鬱蔥雨林聯盟": 15
    },
    "有效票數": 786,
    "無效票數": 3,
    "投票數": 789,
    "已領未投票數": 0,
    "發出票數": 789,
    "用餘票數": 199,
    "選舉人數": 988,
    "投票率": 79.86000061035156
  },
  {
    "行政區別": "岡山區",
    "村里別": "本洲里",
    "候選人票數": {
      "金色曠野同盟": 801,
      "蔚藍海岸陣線": 460,
      "鬱蔥雨林聯盟": 51
    },
    "有效票數": 1312,
    "無效票數": 14,
    "投票數": 1326,
    "已領未投票數": 0,
    "發出票數": 1326,
    "用餘票數": 321,
    "選舉人數": 1647,
    "投票率": 80.51000213623047
  },
  {
    "行政區別": "岡山區",
    "村里別": "嘉興里",
    "候選人票數": {
      "金色曠野同盟": 1731,
      "蔚藍海岸陣線": 735,
      "鬱蔥雨林聯盟": 97
    },
    "有效票數": 2563,
    "無效票數": 21,
    "投票數": 2584,
    "已領未投票數": 0,
    "發出票數": 2584,
    "用餘票數": 719,
    "選舉人數": 3303,
    "投票率": 78.2300033569336
  },
  {
    "行政區別": "岡山區",
    "村里別": "嘉峰里",
    "候選人票數": {
      "金色曠野同盟": 816,
      "蔚藍海岸陣線": 463,
      "鬱蔥雨林聯盟": 32
    },
    "有效票數": 1311,
    "無效票數": 22,
    "投票數": 1333,
    "已領未投票數": 0,
    "發出票數": 1333,
    "用餘票數": 321,
    "選舉人數": 1654,
    "投票率": 80.58999633789062
  },
  {
    "行政區別": "岡山區",
    "村里別": "華崗里",
    "候選人票數": {
      "金色曠野同盟": 924,
      "蔚藍海岸陣線": 248,
      "鬱蔥雨林聯盟": 29
    },
    "有效票數": 1201,
    "無效票數": 4,
    "投票數": 1205,
    "已領未投票數": 0,
    "發出票數": 1205,
    "用餘票數": 235,
    "選舉人數": 1440,
    "投票率": 83.68000030517578
  },
  {
    "行政區別": "岡山區",
    "村里別": "大莊里",
    "候選人票數": {
      "金色曠野同盟": 414,
      "蔚藍海岸陣線": 275,
      "鬱蔥雨林聯盟": 17
    },
    "有效票數": 706,
    "無效票數": 8,
    "投票數": 714,
    "已領未投票數": 0,
    "發出票數": 714,
    "用餘票數": 234,
    "選舉人數": 948,
    "投票率": 75.31999969482422
  },
  {
    "行政區別": "岡山區",
    "村里別": "協榮里",
    "候選人票數": {
      "金色曠野同盟": 637,
      "蔚藍海岸陣線": 883,
      "鬱蔥雨林聯盟": 44
    },
    "有效票數": 1564,
    "無效票數": 20,
    "投票數": 1584,
    "已領未投票數": 0,
    "發出票數": 1584,
    "用餘票數": 469,
    "選舉人數": 2053,
    "投票率": 77.16000366210938
  },
  {
    "行政區別": "岡山區",
    "村里別": "為隨里",
    "候選人票數": {
      "金色曠野同盟": 334,
      "蔚藍海岸陣線": 158,
      "鬱蔥雨林聯盟": 17
    },
    "有效票數": 509,
    "無效票數": 5,
    "投票數": 514,
    "已領未投票數": 0,
    "發出票數": 514,
    "用餘票數": 96,
    "選舉人數": 610,
    "投票率": 84.26000213623047
  },
  {
    "行政區別": "岡山區",
    "村里別": "壽峰里",
    "候選人票數": {
      "金色曠野同盟": 794,
      "蔚藍海岸陣線": 817,
      "鬱蔥雨林聯盟": 55
    },
    "有效票數": 1666,
    "無效票數": 7,
    "投票數": 1673,
    "已領未投票數": 0,
    "發出票數": 1673,
    "用餘票數": 481,
    "選舉人數": 2154,
    "投票率": 77.66999816894531
  },
  {
    "行政區別": "岡山區",
    "村里別": "仁義里",
    "候選人票數": {
      "金色曠野同盟": 73,
      "蔚藍海岸陣線": 1388,
      "鬱蔥雨林聯盟": 31
    },
    "有效票數": 1492,
    "無效票數": 7,
    "投票數": 1499,
    "已領未投票數": 0,
    "發出票數": 1499,
    "用餘票數": 309,
    "選舉人數": 1808,
    "投票率": 82.91000366210938
  }
]