[
  {
    "行政區別": "總計",
    "候選人票數": {
      "鬱蔥雨林聯盟": 11138,
      "蔚藍海岸陣線": 98810,
      "金色曠野同盟": 197342
    },
    "有效票數": 307290,
    "無效票數": 3748,
    "投票數": 311038,
    "已領未投票數": 10,
    "發出票數": 311048,
    "用餘票數": 117592,
    "選舉人數": 428640,
    "投票率": 72.5639
  },
  {
    "行政區別": "太保市",
    "候選人票數": {
      "鬱蔥雨林聯盟": 905,
      "蔚藍海岸陣線": 6934,
      "金色曠野同盟": 14968
    },
    "有效票數": 22807,
    "無效票數": 283,
    "投票數": 23090,
    "已領未投票數": 1,
    "發出票數": 23091,
    "用餘票數": 7599,
    "選舉人數": 30690,
    "投票率": 75.2362
  },
  {
    "行政區別": "朴子市",
    "候選人票數": {
      "鬱蔥雨林聯盟": 823,
      "蔚藍海岸陣線": 7657,
      "金色曠野同盟": 16136
    },
    "有效票數": 24616,
    "無效票數": 297,
    "投票數": 24913,
    "已領未投票數": 1,
    "發出票數": 24914,
    "用餘票數": 9020,
    "選舉人數": 33934,
    "投票率": 73.416
  },
  {
    "行政區別": "布袋鎮",
    "候選人票數": {
      "鬱蔥雨林聯盟": 493,
      "蔚藍海岸陣線": 5408,
      "金色曠野同盟": 10089
    },
    "有效票數": 15990,
    "無效票數": 260,
    "投票數": 16250,
    "已領未投票數": 0,
    "發出票數": 16250,
    "用餘票數": 6833,
    "選舉人數": 23083,
    "投票率": 70.3981
  },
  {
    "行政區別": "大林鎮",
    "候選人票數": {
      "鬱蔥雨林聯盟": 720,
      "蔚藍海岸陣線": 6396,
      "金色曠野同盟": 11839
    },
    "有效票數": 18955,
    "無效票數": 225,
    "投票數": 19180,
    "已領未投票數": 2,
    "發出票數": 19182,
    "用餘票數": 6877,
    "選舉人數": 26059,
    "投票率": 73.6022
  },
  {
    "行政區別": "民雄鄉",
    "候選人票數": {
      "鬱蔥雨林聯盟": 1773,
      "蔚藍海岸陣線": 13576,
      "金色曠野同盟": 28356
    },
    "有效票數": 43705,
    "無效票數": 532,
    "投票數": 44237,
    "已領未投票數": 2,
    "發出票數": 44239,
    "用餘票數": 15282,
    "選舉人數": 59521,
    "投票率": 74.3217
  },
  {
    "行政區別": "溪口鄉",
    "候選人票數": {
      "鬱蔥雨林聯盟": 304,
      "蔚藍海岸陣線": 2305,
      "金色曠野同盟": 6366
    },
    "有效票數": 8975,
    "無效票數": 99,
    "投票數": 9074,
    "已領未投票數": 0,
    "發出票數": 9074,
    "用餘票數": 3434,
    "選舉人數": 12508,
    "投票率": 72.5456
  },
  {
    "行政區別": "新港鄉",
    "候選人票數": {
      "鬱蔥雨林聯盟": 628,
      "蔚藍海岸陣線": 4878,
      "金色曠野同盟": 13732
    },
    "有效票數": 19238,
    "無效票數": 212,
    "投票數": 19450,
    "已領未投票數": 0,
    "發出票數": 19450,
    "用餘票數": 7011,
    "選舉人數": 26461,
    "投票率": 73.5044
  },
  {
    "行政區別": "六腳鄉",
    "候選人票數": {
      "鬱蔥雨林聯盟": 412,
      "蔚藍海岸陣線": 3666,
      "金色曠野同盟": 9667
    },
    "有效票數": 13745,
    "無效票數": 201,
    "投票數": 13946,
    "已領未投票數": 0,
    "發出票數": 13946,
    "用餘票數": 6182,
    "選舉人數": 20128,
    "投票率": 69.2866
  },
  {
    "行政區別": "東石鄉",
    "候選人票數": {
      "鬱蔥雨林聯盟": 512,
      "蔚藍海岸陣線": 4731,
      "金色曠野同盟": 8943
    },
    "有效票數": 14186,
    "無效票數": 218,
    "投票數": 14404,
    "已領未投票數": 1,
    "發出票數": 14405,
    "用餘票數": 6740,
    "選舉人數": 21145,
    "投票率": 68.1201
  },
  {
    "行政區別": "義竹鄉",
    "候選人票數": {
      "鬱蔥雨林聯盟": 384,
      "蔚藍海岸陣線": 3616,
      "金色曠野同盟": 7615
    },
    "有效票數": 11615,
    "無效票數": 167,
    "投票數": 11782,
    "已領未投票數": 0,
    "發出票數": 11782,
    "用餘票數": 4215,
    "選舉人數": 15997,
    "投票率": 73.6513
  },
  {
    "行政區別": "鹿草鄉",
    "候選人票數": {
      "鬱蔥雨林聯盟": 251,
      "蔚藍海岸陣線": 2725,
      "金色曠野同盟": 6276
    },
    "有效票數": 9252,
    "無效票數": 151,
    "投票數": 9403,
    "已領未投票數": 0,
    "發出票數": 9403,
    "用餘票數": 4069,
    "選舉人數": 13472,
    "投票率": 69.7966
  },
  {
    "行政區別": "水上鄉",
    "候選人票數": {
      "鬱蔥雨林聯盟": 1163,
      "蔚藍海岸陣線": 10433,
      "金色曠野同盟": 20011
    },
    "有效票數": 31607,
    "無效票數": 383,
    "投票數": 31990,
    "已領未投票數": 1,
    "發出票數": 31991,
    "用餘票數": 10694,
    "選舉人數": 42685,
    "投票率": 74.9444
  },
  {
    "行政區別": "中埔鄉",
    "候選人票數": {
      "鬱蔥雨林聯盟": 985,
      "蔚藍海岸陣線": 9132,
      "金色曠野同盟": 16947
    },
    "有效票數": 27064,
    "無效票數": 268,
    "投票數": 27332,
    "已領未投票數": 2,
    "發出票數": 27334,
    "用餘票數": 10704,
    "選舉人數": 38038,
    "投票率": 71.8545
  },
  {
    "行政區別": "竹崎鄉",
    "候選人票數": {
      "鬱蔥雨林聯盟": 846,
      "蔚藍海岸陣線": 7404,
      "金色曠野同盟": 13350
    },
    "有效票數": 21600,
    "無效票數": 220,
    "投票數": 21820,
    "已領未投票數": 0,
    "發出票數": 21820,
    "用餘票數": 8387,
    "選舉人數": 30207,
    "投票率": 72.2349
  },
  {
    "行政區別": "梅山鄉",
    "候選人票數": {
      "鬱蔥雨林聯盟": 484,
      "蔚藍海岸陣線": 4306,
      "金色曠野同盟": 6926
    },
    "有效票數": 11716,
    "無效票數": 114,
    "投票數": 11830,
    "已領未投票數": 0,
    "發出票數": 11830,
    "用餘票數": 4664,
    "選舉人數": 16494,
    "投票率": 71.7231
  },
  {
    "行政區別": "番路鄉",
    "候選人票數": {
      "鬱蔥雨林聯盟": 273,
      "蔚藍海岸陣線": 2707,
      "金色曠野同盟": 3966
    },
    "有效票數": 6946,
    "無效票數": 67,
    "投票數": 7013,
    "已領未投票數": 0,
    "發出票數": 7013,
    "用餘票數": 2751,
    "選舉人數": 9764,
    "投票率": 71.8251
  },
  {
    "行政區別": "大埔鄉",
    "候選人票數": {
      "鬱蔥雨林聯盟": 76,
      "蔚藍海岸陣線": 930,
      "金色曠野同盟": 1224
    },
    "有效票數": 2230,
    "無效票數": 23,
    "投票數": 2253,
    "已領未投票數": 0,
    "發出票數": 2253,
    "用餘票數": 1659,
    "選舉人數": 3912,
    "投票率": 57.592
  },
  {
    "行政區別": "阿里山鄉",
    "候選人票數": {
      "鬱蔥雨林聯盟": 106,
      "蔚藍海岸陣線": 2006,
      "金色曠野同盟": 931
    },
    "有效票數": 3043,
    "無效票數": 28,
    "投票數": 3071,
    "已領未投票數": 0,
    "發出票數": 3071,
    "用餘票數": 1471,
    "選舉人數": 4542,
    "投票率": 67.6134
  }
]