[
  {
    "行政區別": "西屯區",
    "村里別": "總計",
    "候選人票數": {
      "鬱蔥雨林聯盟": 6950,
      "蔚藍海岸陣線": 54982,
      "金色曠野同盟": 74475
    },
    "有效票數": 136407,
    "無效票數": 1729,
    "投票數": 138136,
    "已領未投票數": 4,
    "發出票數": 138140,
    "用餘票數": 42868,
    "選舉人數": 181008,
    "投票率": 76.3149
  },
  {
    "行政區別": "西屯區",
    "村里別": "西安里",
    "候選人票數": {
      "鬱蔥雨林聯盟": 174,
      "蔚藍海岸陣線": 1323,
      "金色曠野同盟": 2119
    },
    "有效票數": 3616,
    "無效票數": 52,
    "投票數": 3668,
    "已領未投票數": 0,
    "發出票數": 3668,
    "用餘票數": 987,
    "選舉人數": 4655,
    "投票率": 78.797
  },
  {
    "行政區別": "西屯區",
    "村里別": "至善里",
    "候選人票數": {
      "鬱蔥雨林聯盟": 165,
      "蔚藍海岸陣線": 1317,
      "金色曠野同盟": 1742
    },
    "有效票數": 3224,
    "無效票數": 37,
    "投票數": 3261,
    "已領未投票數": 0,
    "發出票數": 3261,
    "用餘票數": 938,
    "選舉人數": 4199,
    "投票率": 77.6613
  },
  {
    "行政區別": "西屯區",
    "村里別": "西平里",
    "候選人票數": {
      "鬱蔥雨林聯盟": 147,
      "蔚藍海岸陣線": 1665,
      "金色曠野同盟": 1735
    },
    "有效票數": 3547,
    "無效票數": 51,
    "投票數": 3598,
    "已領未投票數": 0,
    "發出票數": 3598,
    "用餘票數": 1211,
    "選舉人數": 4809,
    "投票率": 74.818
  },
  {
    "行政區別": "西屯區",
    "村里別": "西墩里",
    "候選人票數": {
      "鬱蔥雨林聯盟": 218,
      "蔚藍海岸陣線": 1454,
      "金色曠野同盟": 2407
    },
    "有效票數": 4079,
    "無效票數": 45,
    "投票數": 4124,
    "已領未投票數": 0,
    "發出票數": 4124,
    "用餘票數": 1316,
    "選舉人數": 5440,
    "投票率": 75.8088
  },
  {
    "行政區別": "西屯區",
    "村里別": "潮洋里",
    "候選人票數": {
      "鬱蔥雨林聯盟": 207,
      "蔚藍海岸陣線": 1463,
      "金色曠野同盟": 2041
    },
    "有效票數": 3711,
    "無效票數": 59,
    "投票數": 3770,
    "已領未投票數": 0,
    "發出票數": 3770,
    "用餘票數": 1946,
    "選舉人數": 5716,
    "投票率": 65.9552
  },
  {
    "行政區別": "西屯區",
    "村里別": "龍潭里",
    "候選人票數": {
      "鬱蔥雨林聯盟": 20,
      "蔚藍海岸陣線": 182,
      "金色曠野同盟": 421
    },
    "有效票數": 623,
    "無效票數": 9,
    "投票數": 632,
    "已領未投票數": 0,
    "發出票數": 632,
    "用餘票數": 160,
    "選舉人數": 792,
    "投票率": 79.798
  },
  {
    "行政區別": "西屯區",
    "村里別": "惠來里",
    "候選人票數": {
      "鬱蔥雨林聯盟": 494,
      "蔚藍海岸陣線": 4270,
      "金色曠野同盟": 5144
    },
    "有效票數": 9908,
    "無效票數": 105,
    "投票數": 10013,
    "已領未投票數": 0,
    "發出票數": 10013,
    "用餘票數": 3269,
    "選舉人數": 13282,
    "投票率": 75.3877
  },
  {
    "行政區別": "西屯區",
    "村里別": "上石里",
    "候選人票數": {
      "鬱蔥雨林聯盟": 219,
      "蔚藍海岸陣線": 1424,
      "金色曠野同盟": 1922
    },
    "有效票數": 3565,
    "無效票數": 54,
    "投票數": 3619,
    "已領未投票數": 0,
    "發出票數": 3619,
    "用餘票數": 1143,
    "選舉人數": 4762,
    "投票率": 75.9975
  },
  {
    "行政區別": "西屯區",
    "村里別": "上安里",
    "候選人票數": {
      "鬱蔥雨林聯盟": 208,
      "蔚藍海岸陣線": 1432,
      "金色曠野同盟": 2071
    },
    "有效票數": 3711,
    "無效票數": 58,
    "投票數": 3769,
    "已領未投票數": 1,
    "發出票數": 3770,
    "用餘票數": 1150,
    "選舉人數": 4920,
    "投票率": 76.6057
  },
  {
    "行政區別": "西屯區",
    "村里別": "上德里",
    "候選人票數": {
      "鬱蔥雨林聯盟": 172,
      "蔚藍海岸陣線": 1287,
      "金色曠野同盟": 1631
    },
    "有效票數": 3090,
    "無效票數": 41,
    "投票數": 3131,
    "已領未投票數": 0,
    "發出票數": 3131,
    "用餘票數": 898,
    "選舉人數": 4029,
    "投票率": 77.7116
  },
  {
    "行政區別": "西屯區",
    "村里別": "逢甲里",
    "候選人票數": {
      "鬱蔥雨林聯盟": 165,
      "蔚藍海岸陣線": 1248,
      "金色曠野同盟": 1680
    },
    "有效票數": 3093,
    "無效票數": 36,
    "投票數": 3129,
    "已領未投票數": 1,
    "發出票數": 3130,
    "用餘票數": 1016,
    "選舉人數": 4146,
    "投票率": 75.4703
  },
  {
    "行政區別": "西屯區",
    "村里別": "逢福里",
    "候選人票數": {
      "鬱蔥雨林聯盟": 222,
      "蔚藍海岸陣線": 1670,
      "金色曠野同盟": 2133
    },
    "有效票數": 4025,
    "無效票數": 59,
    "投票數": 4084,
    "已領未投票數": 0,
    "發出票數": 4084,
    "用餘票數": 1122,
    "選舉人數": 5206,
    "投票率": 78.4479
  },
  {
    "行政區別": "西屯區",
    "村里別": "鵬程里",
    "候選人票數": {
      "鬱蔥雨林聯盟": 84,
      "蔚藍海岸陣線": 1452,
      "金色曠野同盟": 451
    },
    "有效票數": 1987,
    "無效票數": 28,
    "投票數": 2015,
    "已領未投票數": 0,
    "發出票數": 2015,
    "用餘票數": 660,
    "選舉人數": 2675,
    "投票率": 75.3271
  },
  {
    "行政區別": "西屯區",
    "村里別": "何厝里",
    "候選人票數": {
      "鬱蔥雨林聯盟": 100,
      "蔚藍海岸陣線": 822,
      "金色曠野同盟": 1386
    },
    "有效票數": 2308,
    "無效票數": 38,
    "投票數": 2346,
    "已領未投票數": 0,
    "發出票數": 2346,
    "用餘票數": 756,
    "選舉人數": 3102,
    "投票率": 75.6286
  },
  {
    "行政區別": "西屯區",
    "村里別": "何明里",
    "候選人票數": {
      "鬱蔥雨林聯盟": 123,
      "蔚藍海岸陣線": 1046,
      "金色曠野同盟": 1564
    },
    "有效票數": 2733,
    "無效票數": 26,
    "投票數": 2759,
    "已領未投票數": 0,
    "發出票數": 2759,
    "用餘票數": 751,
    "選舉人數": 3510,
    "投票率": 78.604
  },
  {
    "行政區別": "西屯區",
    "村里別": "何南里",
    "候選人票數": {
      "鬱蔥雨林聯盟": 134,
      "蔚藍海岸陣線": 1284,
      "金色曠野同盟": 1725
    },
    "有效票數": 3143,
    "無效票數": 36,
    "投票數": 3179,
    "已領未投票數": 0,
    "發出票數": 3179,
    "用餘票數": 907,
    "選舉人數": 4086,
    "投票率": 77.8023
  },
  {
    "行政區別": "西屯區",
    "村里別": "何成里",
    "候選人票數": {
      "鬱蔥雨林聯盟": 281,
      "蔚藍海岸陣線": 2105,
      "金色曠野同盟": 2931
    },
    "有效票數": 5317,
    "無效票數": 56,
    "投票數": 5373,
    "已領未投票數": 0,
    "發出票數": 5373,
    "用餘票數": 1595,
    "選舉人數": 6968,
    "投票率": 77.1096
  },
  {
    "行政區別": "西屯區",
    "村里別": "何安里",
    "候選人票數": {
      "鬱蔥雨林聯盟": 185,
      "蔚藍海岸陣線": 1412,
      "金色曠野同盟": 2129
    },
    "有效票數": 3726,
    "無效票數": 46,
    "投票數": 3772,
    "已領未投票數": 0,
    "發出票數": 3772,
    "用餘票數": 1207,
    "選舉人數": 4979,
    "投票率": 75.7582
  },
  {
    "行政區別": "西屯區",
    "村里別": "何仁里",
    "候選人票數": {
      "鬱蔥雨林聯盟": 217,
      "蔚藍海岸陣線": 1661,
      "金色曠野同盟": 2682
    },
    "有效票數": 4560,
    "無效票數": 51,
    "投票數": 4611,
    "已領未投票數": 0,
    "發出票數": 4611,
    "用餘票數": 1415,
    "選舉人數": 6026,
    "投票率": 76.5184
  },
  {
    "行政區別": "西屯區",
    "村里別": "何德里",
    "候選人票數": {
      "鬱蔥雨林聯盟": 139,
      "蔚藍海岸陣線": 1040,
      "金色曠野同盟": 1519
    },
    "有效票數": 2698,
    "無效票數": 43,
    "投票數": 2741,
    "已領未投票數": 0,
    "發出票數": 2741,
    "用餘票數": 773,
    "選舉人數": 3514,
    "投票率": 78.0023
  },
  {
    "行政區別": "西屯區",
    "村里別": "何福里",
    "候選人票數": {
      "鬱蔥雨林聯盟": 175,
      "蔚藍海岸陣線": 1271,
      "金色曠野同盟": 1866
    },
    "有效票數": 3312,
    "無效票數": 43,
    "投票數": 3355,
    "已領未投票數": 0,
    "發出票數": 3355,
    "用餘票數": 897,
    "選舉人數": 4252,
    "投票率": 78.904
  },
  {
    "行政區別": "西屯區",
    "村里別": "何源里",
    "候選人票數": {
      "鬱蔥雨林聯盟": 265,
      "蔚藍海岸陣線": 2034,
      "金色曠野同盟": 2684
    },
    "有效票數": 4983,
    "無效票數": 54,
    "投票數": 5037,
    "已領未投票數": 0,
    "發出票數": 5037,
    "用餘票數": 1458,
    "選舉人數": 6495,
    "投票率": 77.552
  },
  {
    "行政區別": "西屯區",
    "村里別": "大河里",
    "候選人票數": {
      "鬱蔥雨林聯盟": 139,
      "蔚藍海岸陣線": 969,
      "金色曠野同盟": 1766
    },
    "有效票數": 2874,
    "無效票數": 34,
    "投票數": 2908,
    "已領未投票數": 1,
    "發出票數": 2909,
    "用餘票數": 760,
    "選舉人數": 3669,
    "投票率": 79.2587
  },
  {
    "行政區別": "西屯區",
    "村里別": "大石里",
    "候選人票數": {
      "鬱蔥雨林聯盟": 73,
      "蔚藍海岸陣線": 1207,
      "金色曠野同盟": 359
    },
    "有效票數": 1639,
    "無效票數": 30,
    "投票數": 1669,
    "已領未投票數": 0,
    "發出票數": 1669,
    "用餘票數": 469,
    "選舉人數": 2138,
    "投票率": 78.0636
  },
  {
    "行政區別": "西屯區",
    "村里別": "大福里",
    "候選人票數": {
      "鬱蔥雨林聯盟": 125,
      "蔚藍海岸陣線": 1044,
      "金色曠野同盟": 1135
    },
    "有效票數": 2304,
    "無效票數": 42,
    "投票數": 2346,
    "已領未投票數": 1,
    "發出票數": 2347,
    "用餘票數": 768,
    "選舉人數": 3115,
    "投票率": 75.313
  },
  {
    "行政區別": "西屯區",
    "村里別": "大鵬里",
    "候選人票數": {
      "鬱蔥雨林聯盟": 167,
      "蔚藍海岸陣線": 1517,
      "金色曠野同盟": 1831
    },
    "有效票數": 3515,
    "無效票數": 31,
    "投票數": 3546,
    "已領未投票數": 0,
    "發出票數": 3546,
    "用餘票數": 1175,
    "選舉人數": 4721,
    "投票率": 75.1112
  },
  {
    "行政區別": "西屯區",
    "村里別": "港尾里",
    "候選人票數": {
      "鬱蔥雨林聯盟": 167,
      "蔚藍海岸陣線": 1380,
      "金色曠野同盟": 2146
    },
    "有效票數": 3693,
    "無效票數": 38,
    "投票數": 3731,
    "已領未投票數": 0,
    "發出票數": 3731,
    "用餘票數": 1070,
    "選舉人數": 4801,
    "投票率": 77.713
  },
  {
    "行政區別": "西屯區",
    "村里別": "廣福里",
    "候選人票數": {
      "鬱蔥雨林聯盟": 78,
      "蔚藍海岸陣線": 509,
      "金色曠野同盟": 1168
    },
    "有效票數": 1755,
    "無效票數": 34,
    "投票數": 1789,
    "已領未投票數": 0,
    "發出票數": 1789,
    "用餘票數": 472,
    "選舉人數": 2261,
    "投票率": 79.1243
  },
  {
    "行政區別": "西屯區",
    "村里別": "林厝里",
    "候選人票數": {
      "鬱蔥雨林聯盟": 115,
      "蔚藍海岸陣線": 980,
      "金色曠野同盟": 1404
    },
    "有效票數": 2499,
    "無效票數": 32,
    "投票數": 2531,
    "已領未投票數": 0,
    "發出票數": 2531,
    "用餘票數": 749,
    "選舉人數": 3280,
    "投票率": 77.1646
  },
  {
    "行政區別": "西屯區",
    "村里別": "永安里",
    "候選人票數": {
      "鬱蔥雨林聯盟": 457,
      "蔚藍海岸陣線": 3593,
      "金色曠野同盟": 4895
    },
    "有效票數": 8945,
    "無效票數": 104,
    "投票數": 9049,
    "已領未投票數": 0,
    "發出票數": 9049,
    "用餘票數": 3005,
    "選舉人數": 12054,
    "投票率": 75.0705
  },
  {
    "行政區別": "西屯區",
    "村里別": "福安里",
    "候選人票數": {
      "鬱蔥雨林聯盟": 124,
      "蔚藍海岸陣線": 854,
      "金色曠野同盟": 1108
    },
    "有效票數": 2086,
    "無效票數": 20,
    "投票數": 2106,
    "已領未投票數": 0,
    "發出票數": 2106,
    "用餘票數": 569,
    "選舉人數": 2675,
    "投票率": 78.729
  },
  {
    "行政區別": "西屯區",
    "村里別": "福雅里",
    "候選人票數": {
      "鬱蔥雨林聯盟": 257,
      "蔚藍海岸陣線": 1650,
      "金色曠野同盟": 2282
    },
    "有效票數": 4189,
    "無效票數": 51,
    "投票數": 4240,
    "已領未投票數": 0,
    "發出票數": 4240,
    "用餘票數": 1216,
    "選舉人數": 5456,
    "投票率": 77.7126
  },
  {
    "行政區別": "西屯區",
    "村里別": "福林里",
    "候選人票數": {
      "鬱蔥雨林聯盟": 298,
      "蔚藍海岸陣線": 2294,
      "金色曠野同盟": 2830
    },
    "有效票數": 5422,
    "無效票數": 78,
    "投票數": 5500,
    "已領未投票數": 0,
    "發出票數": 5500,
    "用餘票數": 1573,
    "選舉人數": 7073,
    "投票率": 77.7605
  },
  {
    "行政區別": "西屯區",
    "村里別": "福瑞里",
    "候選人票數": {
      "鬱蔥雨林聯盟": 103,
      "蔚藍海岸陣線": 932,
      "金色曠野同盟": 1032
    },
    "有效票數": 2067,
    "無效票數": 22,
    "投票數": 2089,
    "已領未投票數": 0,
    "發出票數": 2089,
    "用餘票數": 757,
    "選舉人數": 2846,
    "投票率": 73.4013
  },
  {
    "行政區別": "西屯區",
    "村里別": "福聯里",
    "候選人票數": {
      "鬱蔥雨林聯盟": 109,
      "蔚藍海岸陣線": 866,
      "金色曠野同盟": 1130
    },
    "有效票數": 2105,
    "無效票數": 29,
    "投票數": 2134,
    "已領未投票數": 0,
    "發出票數": 2134,
    "用餘票數": 879,
    "選舉人數": 3013,
    "投票率": 70.8264
  },
  {
    "行政區別": "西屯區",
    "村里別": "福和里",
    "候選人票數": {
      "鬱蔥雨林聯盟": 151,
      "蔚藍海岸陣線": 996,
      "金色曠野同盟": 2059
    },
    "有效票數": 3206,
    "無效票數": 39,
    "投票數": 3245,
    "已領未投票數": 0,
    "發出票數": 3245,
    "用餘票數": 969,
    "選舉人數": 4214,
    "投票率": 77.0052
  },
  {
    "行政區別": "西屯區",
    "村里別": "福中里",
    "候選人票數": {
      "鬱蔥雨林聯盟": 118,
      "蔚藍海岸陣線": 859,
      "金色曠野同盟": 1412
    },
    "有效票數": 2389,
    "無效票數": 33,
    "投票數": 2422,
    "已領未投票數": 0,
    "發出票數": 2422,
    "用餘票數": 712,
    "選舉人數": 3134,
    "投票率": 77.2814
  },
  {
    "行政區別": "西屯區",
    "村里別": "福恩里",
    "候選人票數": {
      "鬱蔥雨林聯盟": 203,
      "蔚藍海岸陣線": 1385,
      "金色曠野同盟": 1924
    },
    "有效票數": 3512,
    "無效票數": 42,
    "投票數": 3554,
    "已領未投票數": 0,
    "發出票數": 3554,
    "用餘票數": 1043,
    "選舉人數": 4597,
    "投票率": 77.3113
  },
  {
    "行政區別": "西屯區",
    "村里別": "協和里",
    "候選人票數": {
      "鬱蔥雨林聯盟": 152,
      "蔚藍海岸陣線": 1085,
      "金色曠野同盟": 2011
    },
    "有效票數": 3248,
    "無效票數": 43,
    "投票數": 3291,
    "已領未投票數": 0,
    "發出票數": 3291,
    "用餘票數": 1107,
    "選舉人數": 4398,
    "投票率": 74.8295
  }
]