[
  {
    "行政區別": "瑞穗鄉",
    "村里別": "總計",
    "候選人票數": {
      "鬱蔥雨林聯盟": 211,
      "蔚藍海岸陣線": 3856,
      "金色曠野同盟": 1998
    },
    "有效票數": 6065,
    "無效票數": 82,
    "投票數": 6147,
    "已領未投票數": 0,
    "發出票數": 6147,
    "用餘票數": 3711,
    "選舉人數": 9858,
    "投票率": 62.3554
  },
  {
    "行政區別": "瑞穗鄉",
    "村里別": "瑞穗村",
    "候選人票數": {
      "鬱蔥雨林聯盟": 35,
      "蔚藍海岸陣線": 704,
      "金色曠野同盟": 440
    },
    "有效票數": 1179,
    "無效票數": 10,
    "投票數": 1189,
    "已領未投票數": 0,
    "發出票數": 1189,
    "用餘票數": 650,
    "選舉人數": 1839,
    "投票率": 64.6547
  },
  {
    "行政區別": "瑞穗鄉",
    "村里別": "瑞美村",
    "候選人票數": {
      "鬱蔥雨林聯盟": 38,
      "蔚藍海岸陣線": 709,
      "金色曠野同盟": 418
    },
    "有效票數": 1165,
    "無效票數": 11,
    "投票數": 1176,
    "已領未投票數": 0,
    "發出票數": 1176,
    "用餘票數": 568,
    "選舉人數": 1744,
    "投票率": 67.4312
  },
  {
    "行政區別": "瑞穗鄉",
    "村里別": "瑞良村",
    "候選人票數": {
      "鬱蔥雨林聯盟": 17,
      "蔚藍海岸陣線": 206,
      "金色曠野同盟": 129
    },
    "有效票數": 352,
    "無效票數": 3,
    "投票數": 355,
    "已領未投票數": 0,
    "發出票數": 355,
    "用餘票數": 175,
    "選舉人數": 530,
    "投票率": 66.9811
  },
  {
    "行政區別": "瑞穗鄉",
    "村里別": "瑞祥村",
    "候選人票數": {
      "鬱蔥雨林聯盟": 28,
      "蔚藍海岸陣線": 357,
      "金色曠野同盟": 221
    },
    "有效票數": 606,
    "無效票數": 11,
    "投票數": 617,
    "已領未投票數": 0,
    "發出票數": 617,
    "用餘票數": 322,
    "選舉人數": 939,
    "投票率": 65.7082
  },
  {
    "行政區別": "瑞穗鄉",
    "村里別": "瑞北村",
    "候選人票數": {
      "鬱蔥雨林聯盟": 8,
      "蔚藍海岸陣線": 221,
      "金色曠野同盟": 99
    },
    "有效票數": 328,
    "無效票數": 3,
    "投票數": 331,
    "已領未投票數": 0,
    "發出票數": 331,
    "用餘票數": 235,
    "選舉人數": 566,
    "投票率": 58.4806
  },
  {
    "行政區別": "瑞穗鄉",
    "村里別": "舞鶴村",
    "候選人票數": {
      "鬱蔥雨林聯盟": 17,
      "蔚藍海岸陣線": 380,
      "金色曠野同盟": 168
    },
    "有效票數": 565,
    "無效票數": 7,
    "投票數": 572,
    "已領未投票數": 0,
    "發出票數": 572,
    "用餘票數": 349,
    "選舉人數": 921,
    "投票率": 62.1064
  },
  {
    "行政區別": "瑞穗鄉",
    "村里別": "鶴岡村",
    "候選人票數": {
      "鬱蔥雨林聯盟": 24,
      "蔚藍海岸陣線": 349,
      "金色曠野同盟": 109
    },
    "有效票數": 482,
    "無效票數": 6,
    "投票數": 488,
    "已領未投票數": 0,
    "發出票數": 488,
    "用餘票數": 360,
    "選舉人數": 848,
    "投票率": 57.5472
  },
  {
    "行政區別": "瑞穗鄉",
    "村里別": "奇美村",
    "候選人票數": {
      "鬱蔥雨林聯盟": 3,
      "蔚藍海岸陣線": 118,
      "金色曠野同盟": 31
    },
    "有效票數": 152,
    "無效票數": 2,
    "投票數": 154,
    "已領未投票數": 0,
    "發出票數": 154,
    "用餘票數": 174,
    "選舉人數": 328,
    "投票率": 46.9512
  },
  {
    "行政區別": "瑞穗鄉",
    "村里別": "富源村",
    "候選人票數": {
      "鬱蔥雨林聯盟": 17,
      "蔚藍海岸陣線": 270,
      "金色曠野同盟": 149
    },
    "有效票數": 436,
    "無效票數": 12,
    "投票數": 448,
    "已領未投票數": 0,
    "發出票數": 448,
    "用餘票數": 284,
    "選舉人數": 732,
    "投票率": 61.2022
  },
  {
    "行政區別": "瑞穗鄉",
    "村里別": "富民村",
    "候選人票數": {
      "鬱蔥雨林聯盟": 14,
      "蔚藍海岸陣線": 345,
      "金色曠野同盟": 95
    },
    "有效票數": 454,
    "無效票數": 8,
    "投票數": 462,
    "已領未投票數": 0,
    "發出票數": 462,
    "用餘票數": 363,
    "選舉人數": 825,
    "投票率": 56
  },
  {
    "行政區別": "瑞穗鄉",
    "村里別": "富興村",
    "候選人票數": {
      "鬱蔥雨林聯盟": 10,
      "蔚藍海岸陣線": 197,
      "金色曠野同盟": 139
    },
    "有效票數": 346,
    "無效票數": 9,
    "投票數": 355,
    "已領未投票數": 0,
    "發出票數": 355,
    "用餘票數": 231,
    "選舉人數": 586,
    "投票率": 60.5802
  }
]