[
  {
    "行政區別": "土庫鎮",
    "村里別": "總計",
    "候選人票數": {
      "鬱蔥雨林聯盟": 673,
      "蔚藍海岸陣線": 5572,
      "金色曠野同盟": 10744
    },
    "有效票數": 16989,
    "無效票數": 244,
    "投票數": 17233,
    "已領未投票數": 0,
    "發出票數": 17233,
    "用餘票數": 6380,
    "選舉人數": 23613,
    "投票率": 72.981
  },
  {
    "行政區別": "土庫鎮",
    "村里別": "忠正里",
    "候選人票數": {
      "鬱蔥雨林聯盟": 22,
      "蔚藍海岸陣線": 220,
      "金色曠野同盟": 337
    },
    "有效票數": 579,
    "無效票數": 7,
    "投票數": 586,
    "已領未投票數": 0,
    "發出票數": 586,
    "用餘票數": 162,
    "選舉人數": 748,
    "投票率": 78.3422
  },
  {
    "行政區別": "土庫鎮",
    "村里別": "順天里",
    "候選人票數": {
      "鬱蔥雨林聯盟": 29,
      "蔚藍海岸陣線": 243,
      "金色曠野同盟": 371
    },
    "有效票數": 643,
    "無效票數": 9,
    "投票數": 652,
    "已領未投票數": 0,
    "發出票數": 652,
    "用餘票數": 209,
    "選舉人數": 861,
    "投票率": 75.7259
  },
  {
    "行政區別": "土庫鎮",
    "村里別": "宮北里",
    "候選人票數": {
      "鬱蔥雨林聯盟": 44,
      "蔚藍海岸陣線": 364,
      "金色曠野同盟": 608
    },
    "有效票數": 1016,
    "無效票數": 28,
    "投票數": 1044,
    "已領未投票數": 0,
    "發出票數": 1044,
    "用餘票數": 294,
    "選舉人數": 1338,
    "投票率": 78.0269
  },
  {
    "行政區別": "土庫鎮",
    "村里別": "越港里",
    "候選人票數": {
      "鬱蔥雨林聯盟": 22,
      "蔚藍海岸陣線": 349,
      "金色曠野同盟": 426
    },
    "有效票數": 797,
    "無效票數": 10,
    "投票數": 807,
    "已領未投票數": 0,
    "發出票數": 807,
    "用餘票數": 211,
    "選舉人數": 1018,
    "投票率": 79.2731
  },
  {
    "行政區別": "土庫鎮",
    "村里別": "溪邊里",
    "候選人票數": {
      "鬱蔥雨林聯盟": 32,
      "蔚藍海岸陣線": 281,
      "金色曠野同盟": 485
    },
    "有效票數": 798,
    "無效票數": 14,
    "投票數": 812,
    "已領未投票數": 0,
    "發出票數": 812,
    "用餘票數": 260,
    "選舉人數": 1072,
    "投票率": 75.7463
  },
  {
    "行政區別": "土庫鎮",
    "村里別": "石廟里",
    "候選人票數": {
      "鬱蔥雨林聯盟": 98,
      "蔚藍海岸陣線": 667,
      "金色曠野同盟": 1192
    },
    "有效票數": 1957,
    "無效票數": 28,
    "投票數": 1985,
    "已領未投票數": 0,
    "發出票數": 1985,
    "用餘票數": 700,
    "選舉人數": 2685,
    "投票率": 73.9292
  },
  {
    "行政區別": "土庫鎮",
    "村里別": "興新里",
    "候選人票數": {
      "鬱蔥雨林聯盟": 47,
      "蔚藍海岸陣線": 328,
      "金色曠野同盟": 614
    },
    "有效票數": 989,
    "無效票數": 10,
    "投票數": 999,
    "已領未投票數": 0,
    "發出票數": 999,
    "用餘票數": 371,
    "選舉人數": 1370,
    "投票率": 72.9197
  },
  {
    "行政區別": "土庫鎮",
    "村里別": "奮起里",
    "候選人票數": {
      "鬱蔥雨林聯盟": 31,
      "蔚藍海岸陣線": 306,
      "金色曠野同盟": 529
    },
    "有效票數": 866,
    "無效票數": 11,
    "投票數": 877,
    "已領未投票數": 0,
    "發出票數": 877,
    "用餘票數": 386,
    "選舉人數": 1263,
    "投票率": 69.4378
  },
  {
    "行政區別": "土庫鎮",
    "村里別": "埤腳里",
    "候選人票數": {
      "鬱蔥雨林聯盟": 27,
      "蔚藍海岸陣線": 293,
      "金色曠野同盟": 517
    },
    "有效票數": 837,
    "無效票數": 7,
    "投票數": 844,
    "已領未投票數": 0,
    "發出票數": 844,
    "用餘票數": 382,
    "選舉人數": 1226,
    "投票率": 68.8418
  },
  {
    "行政區別": "土庫鎮",
    "村里別": "後埔里",
    "候選人票數": {
      "鬱蔥雨林聯盟": 74,
      "蔚藍海岸陣線": 484,
      "金色曠野同盟": 942
    },
    "有效票數": 1500,
    "無效票數": 22,
    "投票數": 1522,
    "已領未投票數": 0,
    "發出票數": 1522,
    "用餘票數": 676,
    "選舉人數": 2198,
    "投票率": 69.2448
  },
  {
    "行政區別": "土庫鎮",
    "村里別": "崙內里",
    "候選人票數": {
      "鬱蔥雨林聯盟": 34,
      "蔚藍海岸陣線": 305,
      "金色曠野同盟": 700
    },
    "有效票數": 1039,
    "無效票數": 13,
    "投票數": 1052,
    "已領未投票數": 0,
    "發出票數": 1052,
    "用餘票數": 426,
    "選舉人數": 1478,
    "投票率": 71.1773
  },
  {
    "行政區別": "土庫鎮",
    "村里別": "大荖里",
    "候選人票數": {
      "鬱蔥雨林聯盟": 26,
      "蔚藍海岸陣線": 182,
      "金色曠野同盟": 388
    },
    "有效票數": 596,
    "無效票數": 9,
    "投票數": 605,
    "已領未投票數": 0,
    "發出票數": 605,
    "用餘票數": 215,
    "選舉人數": 820,
    "投票率": 73.7805
  },
  {
    "行政區別": "土庫鎮",
    "村里別": "東平里",
    "候選人票數": {
      "鬱蔥雨林聯盟": 52,
      "蔚藍海岸陣線": 330,
      "金色曠野同盟": 912
    },
    "有效票數": 1294,
    "無效票數": 21,
    "投票數": 1315,
    "已領未投票數": 0,
    "發出票數": 1315,
    "用餘票數": 473,
    "選舉人數": 1788,
    "投票率": 73.5459
  },
  {
    "行政區別": "土庫鎮",
    "村里別": "南平里",
    "候選人票數": {
      "鬱蔥雨林聯盟": 42,
      "蔚藍海岸陣線": 387,
      "金色曠野同盟": 833
    },
    "有效票數": 1262,
    "無效票數": 18,
    "投票數": 1280,
    "已領未投票數": 0,
    "發出票數": 1280,
    "用餘票數": 461,
    "選舉人數": 1741,
    "投票率": 73.521
  },
  {
    "行政區別": "土庫鎮",
    "村里別": "西平里",
    "候選人票數": {
      "鬱蔥雨林聯盟": 32,
      "蔚藍海岸陣線": 371,
      "金色曠野同盟": 834
    },
    "有效票數": 1237,
    "無效票數": 19,
    "投票數": 1256,
    "已領未投票數": 0,
    "發出票數": 1256,
    "用餘票數": 505,
    "選舉人數": 1761,
    "投票率": 71.3231
  },
  {
    "行政區別": "土庫鎮",
    "村里別": "北平里",
    "候選人票數": {
      "鬱蔥雨林聯盟": 28,
      "蔚藍海岸陣線": 158,
      "金色曠野同盟": 409
    },
    "有效票數": 595,
    "無效票數": 8,
    "投票數": 603,
    "已領未投票數": 0,
    "發出票數": 603,
    "用餘票數": 247,
    "選舉人數": 850,
    "投票率": 70.9412
  },
  {
    "行政區別": "土庫鎮",
    "村里別": "新庄里",
    "候選人票數": {
      "鬱蔥雨林聯盟": 33,
      "蔚藍海岸陣線": 304,
      "金色曠野同盟": 647
    },
    "有效票數": 984,
    "無效票數": 10,
    "投票數": 994,
    "已領未投票數": 0,
    "發出票數": 994,
    "用餘票數": 402,
    "選舉人數": 1396,
    "投票率": 71.2034
  }
]