[
  {
    "行政區別": "林內鄉",
    "村里別": "總計",
    "候選人票數": {
      "鬱蔥雨林聯盟": 433,
      "蔚藍海岸陣線": 3883,
      "金色曠野同盟": 6595
    },
    "有效票數": 10911,
    "無效票數": 161,
    "投票數": 11072,
    "已領未投票數": 0,
    "發出票數": 11072,
    "用餘票數": 3905,
    "選舉人數": 14977,
    "投票率": 73.9267
  },
  {
    "行政區別": "林內鄉",
    "村里別": "林南村",
    "候選人票數": {
      "鬱蔥雨林聯盟": 44,
      "蔚藍海岸陣線": 297,
      "金色曠野同盟": 399
    },
    "有效票數": 740,
    "無效票數": 9,
    "投票數": 749,
    "已領未投票數": 0,
    "發出票數": 749,
    "用餘票數": 241,
    "選舉人數": 990,
    "投票率": 75.6566
  },
  {
    "行政區別": "林內鄉",
    "村里別": "林中村",
    "候選人票數": {
      "鬱蔥雨林聯盟": 73,
      "蔚藍海岸陣線": 964,
      "金色曠野同盟": 1536
    },
    "有效票數": 2573,
    "無效票數": 41,
    "投票數": 2614,
    "已領未投票數": 0,
    "發出票數": 2614,
    "用餘票數": 903,
    "選舉人數": 3517,
    "投票率": 74.3247
  },
  {
    "行政區別": "林內鄉",
    "村里別": "林北村",
    "候選人票數": {
      "鬱蔥雨林聯盟": 69,
      "蔚藍海岸陣線": 493,
      "金色曠野同盟": 990
    },
    "有效票數": 1552,
    "無效票數": 22,
    "投票數": 1574,
    "已領未投票數": 0,
    "發出票數": 1574,
    "用餘票數": 544,
    "選舉人數": 2118,
    "投票率": 74.3154
  },
  {
    "行政區別": "林內鄉",
    "村里別": "坪頂村",
    "候選人票數": {
      "鬱蔥雨林聯盟": 9,
      "蔚藍海岸陣線": 150,
      "金色曠野同盟": 208
    },
    "有效票數": 367,
    "無效票數": 5,
    "投票數": 372,
    "已領未投票數": 0,
    "發出票數": 372,
    "用餘票數": 141,
    "選舉人數": 513,
    "投票率": 72.5146
  },
  {
    "行政區別": "林內鄉",
    "村里別": "林茂村",
    "候選人票數": {
      "鬱蔥雨林聯盟": 20,
      "蔚藍海岸陣線": 220,
      "金色曠野同盟": 312
    },
    "有效票數": 552,
    "無效票數": 12,
    "投票數": 564,
    "已領未投票數": 0,
    "發出票數": 564,
    "用餘票數": 225,
    "選舉人數": 789,
    "投票率": 71.4829
  },
  {
    "行政區別": "林內鄉",
    "村里別": "九芎村",
    "候選人票數": {
      "鬱蔥雨林聯盟": 67,
      "蔚藍海岸陣線": 643,
      "金色曠野同盟": 1083
    },
    "有效票數": 1793,
    "無效票數": 29,
    "投票數": 1822,
    "已領未投票數": 0,
    "發出票數": 1822,
    "用餘票數": 699,
    "選舉人數": 2521,
    "投票率": 72.2729
  },
  {
    "行政區別": "林內鄉",
    "村里別": "湖本村",
    "候選人票數": {
      "鬱蔥雨林聯盟": 15,
      "蔚藍海岸陣線": 157,
      "金色曠野同盟": 297
    },
    "有效票數": 469,
    "無效票數": 6,
    "投票數": 475,
    "已領未投票數": 0,
    "發出票數": 475,
    "用餘票數": 150,
    "選舉人數": 625,
    "投票率": 76
  },
  {
    "行政區別": "林內鄉",
    "村里別": "烏塗村",
    "候選人票數": {
      "鬱蔥雨林聯盟": 38,
      "蔚藍海岸陣線": 295,
      "金色曠野同盟": 476
    },
    "有效票數": 809,
    "無效票數": 6,
    "投票數": 815,
    "已領未投票數": 0,
    "發出票數": 815,
    "用餘票數": 310,
    "選舉人數": 1125,
    "投票率": 72.4444
  },
  {
    "行政區別": "林內鄉",
    "村里別": "烏麻村",
    "候選人票數": {
      "鬱蔥雨林聯盟": 42,
      "蔚藍海岸陣線": 286,
      "金色曠野同盟": 415
    },
    "有效票數": 743,
    "無效票數": 10,
    "投票數": 753,
    "已領未投票數": 0,
    "發出票數": 753,
    "用餘票數": 266,
    "選舉人數": 1019,
    "投票率": 73.896
  },
  {
    "行政區別": "林內鄉",
    "村里別": "重興村",
    "候選人票數": {
      "鬱蔥雨林聯盟": 56,
      "蔚藍海岸陣線": 378,
      "金色曠野同盟": 879
    },
    "有效票數": 1313,
    "無效票數": 21,
    "投票數": 1334,
    "已領未投票數": 0,
    "發出票數": 1334,
    "用餘票數": 426,
    "選舉人數": 1760,
    "投票率": 75.7955
  }
]