[
  {
    "行政區別": "烏來區",
    "村里別": "總計",
    "候選人票數": {
      "蔚藍海岸陣線": 1156,
      "金色曠野同盟": 1295,
      "鬱蔥雨林聯盟": 586
    },
    "有效票數": 3037,
    "無效票數": 45,
    "投票數": 3082,
    "已領未投票數": 0,
    "發出票數": 3082,
    "用餘票數": 1779,
    "選舉人數": 4861,
    "投票率": 63.400001525878906
  },
  {
    "行政區別": "烏來區",
    "村里別": "忠治里",
    "候選人票數": {
      "蔚藍海岸陣線": 380,
      "金色曠野同盟": 359,
      "鬱蔥雨林聯盟": 168
    },
    "有效票數": 907,
    "無效票數": 17,
    "投票數": 924,
    "已領未投票數": 0,
    "發出票數": 924,
    "用餘票數": 506,
    "選舉人數": 1430,
    "投票率": 64.62000274658203
  },
  {
    "行政區別": "烏來區",
    "村里別": "烏來里",
    "候選人票數": {
      "蔚藍海岸陣線": 484,
      "金色曠野同盟": 605,
      "鬱蔥雨林聯盟": 283
    },
    "有效票數": 1372,
    "無效票數": 19,
    "投票數": 1391,
    "已領未投票數": 0,
    "發出票數": 1391,
    "用餘票數": 779,
    "選舉人數": 2170,
    "投票率": 64.0999984741211
  },
  {
    "行政區別": "烏來區",
    "村里別": "孝義里",
    "候選人票數": {
      "蔚藍海岸陣線": 40,
      "金色曠野同盟": 92,
      "鬱蔥雨林聯盟": 19
    },
    "有效票數": 151,
    "無效票數": 2,
    "投票數": 153,
    "已領未投票數": 0,
    "發出票數": 153,
    "用餘票數": 76,
    "選舉人數": 229,
    "投票率": 66.80999755859375
  },
  {
    "行政區別": "烏來區",
    "村里別": "信賢里",
    "候選人票數": {
      "蔚藍海岸陣線": 106,
      "金色曠野同盟": 156,
      "鬱蔥雨林聯盟": 40
    },
    "有效票數": 302,
    "無效票數": 3,
    "投票數": 305,
    "已領未投票數": 0,
    "發出票數": 305,
    "用餘票數": 182,
    "選舉人數": 487,
    "投票率": 62.630001068115234
  },
  {
    "行政區別": "烏來區",
    "村里別": "福山里",
    "候選人票數": {
      "蔚藍海岸陣線": 146,
      "金色曠野同盟": 83,
      "鬱蔥雨林聯盟": 76
    },
    "有效票數": 305,
    "無效票數": 4,
    "投票數": 309,
    "已領未投票數": 0,
    "發出票數": 309,
    "用餘票數": 236,
    "選舉人數": 545,
    "投票率": 56.70000076293945
  }
]