[
  {
    "行政區別": "六甲區",
    "村里別": "總計",
    "候選人票數": {
      "蔚藍海岸陣線": 2107,
      "金色曠野同盟": 8599,
      "鬱蔥雨林聯盟": 1044
    },
    "有效票數": 11750,
    "無效票數": 175,
    "投票數": 11925,
    "已領未投票數": 0,
    "發出票數": 11925,
    "用餘票數": 6678,
    "選舉人數": 18603,
    "投票率": 64.0999984741211
  },
  {
    "行政區別": "六甲區",
    "村里別": "六甲里",
    "候選人票數": {
      "蔚藍海岸陣線": 359,
      "金色曠野同盟": 1282,
      "鬱蔥雨林聯盟": 161
    },
    "有效票數": 1802,
    "無效票數": 26,
    "投票數": 1828,
    "已領未投票數": 0,
    "發出票數": 1828,
    "用餘票數": 1003,
    "選舉人數": 2831,
    "投票率": 64.56999969482422
  },
  {
    "行政區別": "六甲區",
    "村里別": "甲東里",
    "候選人票數": {
      "蔚藍海岸陣線": 283,
      "金色曠野同盟": 1177,
      "鬱蔥雨林聯盟": 129
    },
    "有效票數": 1589,
    "無效票數": 37,
    "投票數": 1626,
    "已領未投票數": 0,
    "發出票數": 1626,
    "用餘票數": 947,
    "選舉人數": 2573,
    "投票率": 63.189998626708984
  },
  {
    "行政區別": "六甲區",
    "村里別": "甲南里",
    "候選人票數": {
      "蔚藍海岸陣線": 161,
      "金色曠野同盟": 616,
      "鬱蔥雨林聯盟": 72
    },
    "有效票數": 849,
    "無效票數": 6,
    "投票數": 855,
    "已領未投票數": 0,
    "發出票數": 855,
    "用餘票數": 487,
    "選舉人數": 1342,
    "投票率": 63.709999084472656
  },
  {
    "行政區別": "六甲區",
    "村里別": "龍湖里",
    "候選人票數": {
      "蔚藍海岸陣線": 95,
      "金色曠野同盟": 484,
      "鬱蔥雨林聯盟": 47
    },
    "有效票數": 626,
    "無效票數": 5,
    "投票數": 631,
    "已領未投票數": 0,
    "發出票數": 631,
    "用餘票數": 389,
    "選舉人數": 1020,
    "投票率": 61.86000061035156
  },
  {
    "行政區別": "六甲區",
    "村里別": "七甲里",
    "候選人票數": {
      "蔚藍海岸陣線": 75,
      "金色曠野同盟": 484,
      "鬱蔥雨林聯盟": 36
    },
    "有效票數": 595,
    "無效票數": 16,
    "投票數": 611,
    "已領未投票數": 0,
    "發出票數": 611,
    "用餘票數": 286,
    "選舉人數": 897,
    "投票率": 68.12000274658203
  },
  {
    "行政區別": "六甲區",
    "村里別": "二甲里",
    "候選人票數": {
      "蔚藍海岸陣線": 354,
      "金色曠野同盟": 1473,
      "鬱蔥雨林聯盟": 185
    },
    "有效票數": 2012,
    "無效票數": 24,
    "投票數": 2036,
    "已領未投票數": 0,
    "發出票數": 2036,
    "用餘票數": 1122,
    "選舉人數": 3158,
    "投票率": 64.47000122070312
  },
  {
    "行政區別": "六甲區",
    "村里別": "水林里",
    "候選人票數": {
      "蔚藍海岸陣線": 228,
      "金色曠野同盟": 1018,
      "鬱蔥雨林聯盟": 148
    },
    "有效票數": 1394,
    "無效票數": 27,
    "投票數": 1421,
    "已領未投票數": 0,
    "發出票數": 1421,
    "用餘票數": 683,
    "選舉人數": 2104,
    "投票率": 67.54000091552734
  },
  {
    "行政區別": "六甲區",
    "村里別": "中社里",
    "候選人票數": {
      "蔚藍海岸陣線": 200,
      "金色曠野同盟": 733,
      "鬱蔥雨林聯盟": 80
    },
    "有效票數": 1013,
    "無效票數": 14,
    "投票數": 1027,
    "已領未投票數": 0,
    "發出票數": 1027,
    "用餘票數": 556,
    "選舉人數": 1583,
    "投票率": 64.87999725341797
  },
  {
    "行政區別": "六甲區",
    "村里別": "龜港里",
    "候選人票數": {
      "蔚藍海岸陣線": 147,
      "金色曠野同盟": 500,
      "鬱蔥雨林聯盟": 88
    },
    "有效票數": 735,
    "無效票數": 3,
    "投票數": 738,
    "已領未投票數": 0,
    "發出票數": 738,
    "用餘票數": 358,
    "選舉人數": 1096,
    "投票率": 67.33999633789062
  },
  {
    "行政區別": "六甲區",
    "村里別": "菁埔里",
    "候選人票數": {
      "蔚藍海岸陣線": 69,
      "金色曠野同盟": 281,
      "鬱蔥雨林聯盟": 35
    },
    "有效票數": 385,
    "無效票數": 8,
    "投票數": 393,
    "已領未投票數": 0,
    "發出票數": 393,
    "用餘票數": 211,
    "選舉人數": 604,
    "投票率": 65.06999969482422
  },
  {
    "行政區別": "六甲區",
    "村里別": "王爺里",
    "候選人票數": {
      "蔚藍海岸陣線": 68,
      "金色曠野同盟": 314,
      "鬱蔥雨林聯盟": 33
    },
    "有效票數": 415,
    "無效票數": 7,
    "投票數": 422,
    "已領未投票數": 0,
    "發出票數": 422,
    "用餘票數": 330,
    "選舉人數": 752,
    "投票率": 56.119998931884766
  },
  {
    "行政區別": "六甲區",
    "村里別": "大丘里",
    "候選人票數": {
      "蔚藍海岸陣線": 68,
      "金色曠野同盟": 237,
      "鬱蔥雨林聯盟": 30
    },
    "有效票數": 335,
    "無效票數": 2,
    "投票數": 337,
    "已領未投票數": 0,
    "發出票數": 337,
    "用餘票數": 306,
    "選舉人數": 643,
    "投票率": 52.40999984741211
  }
]