[
  {
    "行政區別": "卑南鄉",
    "村里別": "總計",
    "候選人票數": {
      "蔚藍海岸陣線": 3374,
      "金色曠野同盟": 3596,
      "鬱蔥雨林聯盟": 1338
    },
    "有效票數": 8308,
    "無效票數": 110,
    "投票數": 8418,
    "已領未投票數": 0,
    "發出票數": 8418,
    "用餘票數": 6182,
    "選舉人數": 14600,
    "投票率": 57.65999984741211
  },
  {
    "行政區別": "卑南鄉",
    "村里別": "賓朗村",
    "候選人票數": {
      "蔚藍海岸陣線": 445,
      "金色曠野同盟": 657,
      "鬱蔥雨林聯盟": 172
    },
    "有效票數": 1274,
    "無效票數": 18,
    "投票數": 1292,
    "已領未投票數": 0,
    "發出票數": 1292,
    "用餘票數": 853,
    "選舉人數": 2145,
    "投票率": 60.22999954223633
  },
  {
    "行政區別": "卑南鄉",
    "村里別": "美農村",
    "候選人票數": {
      "蔚藍海岸陣線": 130,
      "金色曠野同盟": 341,
      "鬱蔥雨林聯盟": 71
    },
    "有效票數": 542,
    "無效票數": 6,
    "投票數": 548,
    "已領未投票數": 0,
    "發出票數": 548,
    "用餘票數": 466,
    "選舉人數": 1014,
    "投票率": 54.040000915527344
  },
  {
    "行政區別": "卑南鄉",
    "村里別": "初鹿村",
    "候選人票數": {
      "蔚藍海岸陣線": 274,
      "金色曠野同盟": 337,
      "鬱蔥雨林聯盟": 118
    },
    "有效票數": 729,
    "無效票數": 12,
    "投票數": 741,
    "已領未投票數": 0,
    "發出票數": 741,
    "用餘票數": 518,
    "選舉人數": 1259,
    "投票率": 58.86000061035156
  },
  {
    "行政區別": "卑南鄉",
    "村里別": "明峰村",
    "候選人票數": {
      "蔚藍海岸陣線": 207,
      "金色曠野同盟": 296,
      "鬱蔥雨林聯盟": 97
    },
    "有效票數": 600,
    "無效票數": 4,
    "投票數": 604,
    "已領未投票數": 0,
    "發出票數": 604,
    "用餘票數": 558,
    "選舉人數": 1162,
    "投票率": 51.97999954223633
  },
  {
    "行政區別": "卑南鄉",
    "村里別": "嘉豐村",
    "候選人票數": {
      "蔚藍海岸陣線": 81,
      "金色曠野同盟": 117,
      "鬱蔥雨林聯盟": 25
    },
    "有效票數": 223,
    "無效票數": 5,
    "投票數": 228,
    "已領未投票數": 0,
    "發出票數": 228,
    "用餘票數": 268,
    "選舉人數": 496,
    "投票率": 45.970001220703125
  },
  {
    "行政區別": "卑南鄉",
    "村里別": "太平村",
    "候選人票數": {
      "蔚藍海岸陣線": 735,
      "金色曠野同盟": 634,
      "鬱蔥雨林聯盟": 257
    },
    "有效票數": 1626,
    "無效票數": 25,
    "投票數": 1651,
    "已領未投票數": 0,
    "發出票數": 1651,
    "用餘票數": 1225,
    "選舉人數": 2876,
    "投票率": 57.40999984741211
  },
  {
    "行政區別": "卑南鄉",
    "村里別": "泰安村",
    "候選人票數": {
      "蔚藍海岸陣線": 285,
      "金色曠野同盟": 196,
      "鬱蔥雨林聯盟": 163
    },
    "有效票數": 644,
    "無效票數": 5,
    "投票數": 649,
    "已領未投票數": 0,
    "發出票數": 649,
    "用餘票數": 413,
    "選舉人數": 1062,
    "投票率": 61.11000061035156
  },
  {
    "行政區別": "卑南鄉",
    "村里別": "利嘉村",
    "候選人票數": {
      "蔚藍海岸陣線": 334,
      "金色曠野同盟": 150,
      "鬱蔥雨林聯盟": 120
    },
    "有效票數": 604,
    "無效票數": 14,
    "投票數": 618,
    "已領未投票數": 0,
    "發出票數": 618,
    "用餘票數": 407,
    "選舉人數": 1025,
    "投票率": 60.290000915527344
  },
  {
    "行政區別": "卑南鄉",
    "村里別": "東興村",
    "候選人票數": {
      "蔚藍海岸陣線": 426,
      "金色曠野同盟": 102,
      "鬱蔥雨林聯盟": 133
    },
    "有效票數": 661,
    "無效票數": 8,
    "投票數": 669,
    "已領未投票數": 0,
    "發出票數": 669,
    "用餘票數": 467,
    "選舉人數": 1136,
    "投票率": 58.88999938964844
  },
  {
    "行政區別": "卑南鄉",
    "村里別": "溫泉村",
    "候選人票數": {
      "蔚藍海岸陣線": 181,
      "金色曠野同盟": 411,
      "鬱蔥雨林聯盟": 85
    },
    "有效票數": 677,
    "無效票數": 7,
    "投票數": 684,
    "已領未投票數": 0,
    "發出票數": 684,
    "用餘票數": 454,
    "選舉人數": 1138,
    "投票率": 60.11000061035156
  },
  {
    "行政區別": "卑南鄉",
    "村里別": "富山村",
    "候選人票數": {
      "蔚藍海岸陣線": 120,
      "金色曠野同盟": 111,
      "鬱蔥雨林聯盟": 38
    },
    "有效票數": 269,
    "無效票數": 3,
    "投票數": 272,
    "已領未投票數": 0,
    "發出票數": 272,
    "用餘票數": 237,
    "選舉人數": 509,
    "投票率": 53.439998626708984
  },
  {
    "行政區別": "卑南鄉",
    "村里別": "富源村",
    "候選人票數": {
      "蔚藍海岸陣線": 49,
      "金色曠野同盟": 144,
      "鬱蔥雨林聯盟": 19
    },
    "有效票數": 212,
    "無效票數": 2,
    "投票數": 214,
    "已領未投票數": 0,
    "發出票數": 214,
    "用餘票數": 136,
    "選舉人數": 350,
    "投票率": 61.13999938964844
  },
  {
    "行政區別": "卑南鄉",
    "村里別": "利吉村",
    "候選人票數": {
      "蔚藍海岸陣線": 107,
      "金色曠野同盟": 100,
      "鬱蔥雨林聯盟": 40
    },
    "有效票數": 247,
    "無效票數": 1,
    "投票數": 248,
    "已領未投票數": 0,
    "發出票數": 248,
    "用餘票數": 180,
    "選舉人數": 428,
    "投票率": 57.939998626708984
  }
]